dataclass_factory/__init__.py
dataclass_factory/common.py
dataclass_factory/deprecated_stuff.py
dataclass_factory/exceptions.py
dataclass_factory/factory.py
dataclass_factory/fields.py
dataclass_factory/generics.py
dataclass_factory/jsonschema.py
dataclass_factory/naming.py
dataclass_factory/parsers.py
dataclass_factory/path_utils.py
dataclass_factory/py.typed
dataclass_factory/schema.py
dataclass_factory/schema_helpers.py
dataclass_factory/serializers.py
dataclass_factory/type_detection.py
dataclass_factory/validators.py
dataclass_factory-2.15.dist-info/LICENSE
dataclass_factory-2.15.dist-info/METADATA
dataclass_factory-2.15.dist-info/WHEEL
dataclass_factory-2.15.dist-info/top_level.txt
dataclass_factory-2.15.dist-info/RECORD
