Metadata-Version: 2.1
Name: dataclass-factory
Version: 2.15
Summary: An utility class for creating instances of dataclasses
Home-page: https://github.com/tishka17/dataclass_factory
Author: A. Tikhonov
Author-email: 17@itishka.org
License: Apache2
Classifier: Operating System :: OS Independent
Classifier: Intended Audience :: Developers
Classifier: License :: OSI Approved :: Apache Software License
Classifier: Programming Language :: Python :: 3
Requires-Python: >=3.6
License-File: LICENSE
Requires-Dist: dataclasses ; python_version < "3.7"
